crawlab_mcp/__init__.py
crawlab_mcp/cli.py
crawlab_mcp/agents/__init__.py
crawlab_mcp/agents/task_planner.py
crawlab_mcp/clients/__init__.py
crawlab_mcp/clients/client.py
crawlab_mcp/clients/console_client.py
crawlab_mcp/llm_providers/__init__.py
crawlab_mcp/llm_providers/anthropic.py
crawlab_mcp/llm_providers/azure_openai.py
crawlab_mcp/llm_providers/base.py
crawlab_mcp/llm_providers/factory.py
crawlab_mcp/llm_providers/openai_compatible.py
crawlab_mcp/parsers/__init__.py
crawlab_mcp/parsers/openapi.py
crawlab_mcp/servers/__init__.py
crawlab_mcp/servers/server.py
crawlab_mcp/utils/__init__.py
crawlab_mcp/utils/constants.py
crawlab_mcp/utils/http.py
crawlab_mcp/utils/tools.py
mseep_crawlab_mcp-0.7.4.dist-info/METADATA
mseep_crawlab_mcp-0.7.4.dist-info/WHEEL
mseep_crawlab_mcp-0.7.4.dist-info/entry_points.txt
mseep_crawlab_mcp-0.7.4.dist-info/top_level.txt
mseep_crawlab_mcp-0.7.4.dist-info/RECORD
